applot/__init__.py
applot/util.py
applot/plot/HBarPlot.py
applot/plot/LinePlot.py
applot/plot/ScatterPlot.py
applot/plot/Slopegraph.py
applot/plot/SqAreaPlot.py
applot/plot/StackedHBarPlot.py
applot/plot/StackedVBarPlot.py
applot/plot/VBarPlot.py
applot/plot/__init__.py
applot/plot/colors.py
applot/plot/base/PlotAxis.py
applot/plot/base/PlotBase.py
applot/plot/base/PlotGrid.py
applot/plot/base/PlotInner.py
applot/plot/base/PlotLegend.py
applot/plot/base/PlotObject.py
applot/plot/base/PlotTitle.py
applot/plot/base/_Pos.py
applot/plot/base/__init__.py
applot/svg/Circle.py
applot/svg/Defs.py
applot/svg/Element.py
applot/svg/Group.py
applot/svg/Line.py
applot/svg/Path.py
applot/svg/Polygon.py
applot/svg/Polyline.py
applot/svg/Rect.py
applot/svg/SVG.py
applot/svg/Style.py
applot/svg/Text.py
applot/svg/__init__.py
applot-0.1.0.dist-info/LICENSE
applot-0.1.0.dist-info/METADATA
applot-0.1.0.dist-info/WHEEL
applot-0.1.0.dist-info/top_level.txt
applot-0.1.0.dist-info/RECORD
